LICENSE
MANIFEST.in
README.rst
requirements.txt
setup.py
free_tls_certificates/__init__.py
free_tls_certificates/client.py
free_tls_certificates/driver.py
free_tls_certificates/utils.py
free_tls_certificates.egg-info/PKG-INFO
free_tls_certificates.egg-info/SOURCES.txt
free_tls_certificates.egg-info/dependency_links.txt
free_tls_certificates.egg-info/entry_points.txt
free_tls_certificates.egg-info/requires.txt
free_tls_certificates.egg-info/top_level.txt