Metadata-Version: 1.0
Name: free-tls-certificates
Version: 0.1.3
Summary: A simple client/tool for Let's Encrypt or any ACME server that issues SSL certificates.
Home-page: https://github.com/mail-in-a-box/free_tls_certificates
Author: Joshua Tauberer
Author-email: jt@occams.info
License: CC0 (copyright waived)
Keywords: tls ssl certificate acme letsencrypt
Platform: UNKNOWN
